{
  "_source": "EF EPI 2025 (ef.edu/epi) + native English countries (700) + regional estimates",
  "_updated": "2026-03-08",
  "_bands": {
    "NATIVE": "700 (native English-speaking countries)",
    "VERY_HIGH": "600-699",
    "HIGH": "550-599",
    "MODERATE": "500-549",
    "LOW": "450-499",
    "VERY_LOW": "below 450"
  },
  "_notes": "Keys match city slug country suffix. Collector matches via city.country contains.",
  "scores": {
    "australia": 700,
    "new-zealand": 700,
    "united-kingdom": 700,
    "united-states": 700,
    "jamaica": 700,
    "canada": 700,
    "belize": 700,
    "guam": 700,
    "ireland": 700,
    "bahamas": 700,
    "cayman-islands": 700,
    "grenada": 700,
    "guyana": 700,
    "jersey": 700,
    "tobago": 700,
    "south-georgia-and-the-south-sandwich-islands": 700,
    "helena": 700,
    "british-virgin-islands": 700,
    "barbados": 700,
    "bermuda": 700,
    "falkland-islands": 700,
    "gibraltar": 700,
    "united-states-virgin-islands": 700,
    "barbuda": 700,
    "netherlands": 636,
    "iceland": 620,
    "malta": 620,
    "norway": 610,
    "singapore": 609,
    "sweden": 608,
    "croatia": 607,
    "portugal": 605,
    "denmark": 603,
    "greece": 602,
    "puerto-rico": 600,
    "austria": 600,
    "cook-islands": 600,
    "maarten": 600,
    "germany": 598,
    "south-africa": 594,
    "romania": 593,
    "belgium": 592,
    "finland": 590,
    "poland": 588,
    "bulgaria": 586,
    "hungary": 585,
    "slovakia": 584,
    "kenya": 581,
    "slovenia": 580,
    "fiji": 580,
    "estonia": 578,
    "luxembourg": 576,
    "philippines": 570,
    "lithuania": 569,
    "serbia": 568,
    "czechia": 567,
    "republic": 567,
    "malaysia": 566,
    "suriname": 566,
    "argentina": 562,
    "aruba": 560,
    "latvia": 560,
    "mauritius": 560,
    "seychelles": 560,
    "monaco": 560,
    "cyprus": 558,
    "nigeria": 557,
    "switzerland": 550,
    "brunei": 550,
    "greenland": 550,
    "hong-kong": 549,
    "honduras": 545,
    "georgia": 543,
    "andorra": 540,
    "montenegro": 540,
    "botswana": 540,
    "belarus": 539,
    "spain": 538,
    "uruguay": 538,
    "armenia": 537,
    "moldova": 536,
    "ukraine": 535,
    "costa-rica": 534,
    "ghana": 534,
    "albania": 533,
    "russia": 532,
    "paraguay": 531,
    "bosnia": 530,
    "curacao": 530,
    "zimbabwe": 530,
    "samoa": 530,
    "italy": 528,
    "bolivia": 525,
    "chile": 525,
    "france": 524,
    "south-korea": 523,
    "israel": 522,
    "nepal": 520,
    "taiwan": 520,
    "zambia": 520,
    "namibia": 520,
    "cuba": 520,
    "peru": 519,
    "uganda": 518,
    "el-salvador": 513,
    "kosovo": 510,
    "macedonia": 510,
    "gambia": 510,
    "venezuela": 510,
    "tonga": 510,
    "guatemala": 507,
    "dominican-republic": 503,
    "nicaragua": 502,
    "bangladesh": 500,
    "maldives": 500,
    "liberia": 500,
    "city": 500,
    "vanuatu": 500,
    "iran": 499,
    "vietnam": 498,
    "ethiopia": 498,
    "turkey": 497,
    "tunisia": 496,
    "mozambique": 496,
    "pakistan": 493,
    "lebanon": 492,
    "india": 490,
    "bahrain": 490,
    "leone": 490,
    "tuvalu": 490,
    "united-arab-emirates": 489,
    "panama": 488,
    "tanzania": 487,
    "sri-lanka": 486,
    "colombia": 485,
    "bhutan": 480,
    "lesotho": 480,
    "solomon-islands": 480,
    "qatar": 480,
    "morocco": 479,
    "syria": 473,
    "algeria": 471,
    "papua-new-guinea": 470,
    "bali-indonesia": 468,
    "indonesia": 468,
    "brazil": 466,
    "ecuador": 465,
    "egypt": 465,
    "mongolia": 464,
    "madagascar": 463,
    "azerbaijan": 462,
    "mexico": 459,
    "kyrgyzstan": 457,
    "cape-verde": 456,
    "kuwait": 456,
    "china": 455,
    "japan": 454,
    "guadeloupe": 450,
    "martinique": 450,
    "myanmar": 449,
    "palestine": 448,
    "malawi": 447,
    "afghanistan": 447,
    "cameroon": 445,
    "caledonia": 440,
    "guiana": 440,
    "uzbekistan": 439,
    "haiti": 432,
    "sudan": 432,
    "jordan": 431,
    "kurdistan": 430,
    "eritrea": 430,
    "senegal": 429,
    "kazakhstan": 427,
    "oman": 421,
    "djibouti": 420,
    "guinea": 420,
    "saudi-arabia": 417,
    "thailand": 415,
    "iraq": 414,
    "tajikistan": 412,
    "gabon": 410,
    "angola": 409,
    "cambodia": 408,
    "libya": 405,
    "rwanda": 401,
    "laos": 400,
    "congo": 400,
    "togo": 400,
    "timor": 400,
    "sahara": 400,
    "mauritania": 400,
    "divoire": 399,
    "somalia": 399,
    "yemen": 394,
    "faso": 390,
    "chad": 390,
    "mali": 390,
    "niger": 380,
    "turkmenistan": 380,
    "north-korea": 350
  }
}
